ckdl-1.0.dist-info/RECORD
ckdl-1.0.dist-info/WHEEL
ckdl-1.0.dist-info/top_level.txt
ckdl-1.0.dist-info/METADATA
ckdl-1.0.dist-info/licenses/COPYING
ckdl/_ckdl.cpython-314-darwin.so
ckdl/__init__.py
