Metadata-Version: 2.4
Name: ckdl
Version: 1.0
Summary: KDL parser and writer with a C back-end
Home-page: https://github.com/tjol/ckdl
Author: Thomas Jollans
Project-URL: Documentation, https://ckdl.readthedocs.io/
Keywords: kdl parser configuration
Classifier: Development Status :: 5 - Production/Stable
Classifier: Intended Audience :: Developers
Classifier: License :: OSI Approved :: MIT License
Classifier: Programming Language :: Python :: 3
License-File: COPYING
Dynamic: author
Dynamic: classifier
Dynamic: description
Dynamic: description-content-type
Dynamic: home-page
Dynamic: keywords
Dynamic: license-file
Dynamic: project-url
Dynamic: summary
